{
  "version": "2.0",
  "pages": [
    {
      "name": "Page 1",
      "section": "why all created humans and form where",
      "strokes": [
        {
          "points": [
            [
              276.6,
              17.60000000000001,
              1.0
            ],
            [
              274.20000000000005,
              25.599999999999994,
              1.0
            ],
            [
              270.20000000000005,
              37.599999999999994,
              1.0
            ],
            [
              255.8,
              70.4,
              1.0
            ],
            [
              251.0,
              78.4,
              1.0
            ],
            [
              249.40000000000003,
              82.4,
              1.0
            ],
            [
              247.0,
              87.20000000000005,
              1.0
            ],
            [
              243.8,
              92.0,
              1.0
            ],
            [
              241.40000000000003,
              95.20000000000005,
              1.0
            ],
            [
              240.60000000000002,
              96.80000000000001,
              1.0
            ],
            [
              238.2,
              100.0,
              1.0
            ],
            [
              235.8,
              102.4,
              1.0
            ],
            [
              233.40000000000003,
              104.80000000000001,
              1.0
            ],
            [
              231.0,
              105.60000000000002,
              1.0
            ],
            [
              229.40000000000003,
              107.20000000000002,
              1.0
            ],
            [
              226.2,
              108.80000000000001,
              1.0
            ],
            [
              223.0,
              109.60000000000002,
              1.0
            ],
            [
              221.40000000000003,
              109.60000000000002,
              1.0
            ],
            [
              217.40000000000003,
              109.60000000000002,
              1.0
            ],
            [
              214.20000000000002,
              109.60000000000002,
              1.0
            ],
            [
              212.60000000000002,
              109.60000000000002,
              1.0
            ],
            [
              211.0,
              109.60000000000002,
              1.0
            ],
            [
              207.0,
              109.60000000000002,
              1.0
            ],
            [
              204.60000000000002,
              108.80000000000001,
              1.0
            ],
            [
              202.20000000000002,
              108.0,
              1.0
            ],
            [
              201.4,
              106.4,
              1.0
            ],
            [
              199.8,
              104.80000000000001,
              1.0
            ],
            [
              197.4,
              103.20000000000002,
              1.0
            ],
            [
              196.60000000000002,
              100.80000000000001,
              1.0
            ],
            [
              195.8,
              99.20000000000002,
              1.0
            ],
            [
              194.20000000000002,
              97.60000000000002,
              1.0
            ],
            [
              193.4,
              95.20000000000005,
              1.0
            ],
            [
              193.4,
              94.4,
              1.0
            ],
            [
              193.4,
              92.80000000000001,
              1.0
            ],
            [
              193.4,
              90.4,
              1.0
            ],
            [
              193.4,
              89.60000000000002,
              1.0
            ],
            [
              194.20000000000002,
              88.0,
              1.0
            ],
            [
              195.0,
              88.0,
              1.0
            ],
            [
              195.0,
              85.60000000000002,
              1.0
            ],
            [
              195.8,
              85.60000000000002,
              1.0
            ],
            [
              196.60000000000002,
              84.0,
              1.0
            ],
            [
              198.20000000000002,
              84.0,
              1.0
            ],
            [
              200.60000000000002,
              84.0,
              1.0
            ],
            [
              202.20000000000002,
              84.0,
              1.0
            ],
            [
              204.60000000000002,
              84.0,
              1.0
            ],
            [
              207.8,
              85.60000000000002,
              1.0
            ],
            [
              210.20000000000002,
              88.0,
              1.0
            ],
            [
              215.8,
              90.4,
              1.0
            ],
            [
              219.8,
              94.4,
              1.0
            ],
            [
              227.0,
              100.80000000000001,
              1.0
            ],
            [
              234.2,
              107.20000000000002,
              1.0
            ],
            [
              240.60000000000002,
              112.80000000000001,
              1.0
            ],
            [
              247.0,
              119.20000000000002,
              1.0
            ],
            [
              251.0,
              123.20000000000002,
              1.0
            ],
            [
              258.2,
              132.0,
              1.0
            ],
            [
              266.20000000000005,
              143.20000000000002,
              1.0
            ],
            [
              271.8,
              152.8,
              1.0
            ],
            [
              282.20000000000005,
              169.60000000000002,
              1.0
            ],
            [
              292.6,
              190.40000000000003,
              1.0
            ],
            [
              301.4000000000001,
              206.4000000000001,
              1.0
            ],
            [
              308.6,
              219.20000000000005,
              1.0
            ],
            [
              314.20000000000005,
              229.60000000000002,
              1.0
            ],
            [
              320.6,
              239.20000000000005,
              1.0
            ],
            [
              326.20000000000005,
              246.4000000000001,
              1.0
            ],
            [
              331.0,
              253.60000000000002,
              1.0
            ],
            [
              335.0,
              257.6,
              1.0
            ],
            [
              337.4000000000001,
              262.4000000000001,
              1.0
            ],
            [
              340.6,
              265.6,
              1.0
            ],
            [
              341.4000000000001,
              267.20000000000005,
              1.0
            ],
            [
              343.0,
              268.0,
              1.0
            ],
            [
              343.8,
              268.8,
              1.0
            ],
            [
              344.6,
              269.6,
              1.0
            ],
            [
              344.6,
              270.4000000000001,
              1.0
            ],
            [
              345.4000000000001,
              270.4000000000001,
              1.0
            ],
            [
              346.20000000000005,
              271.20000000000005,
              1.0
            ]
          ],
          "color": "#0000ff",
          "width": 10.0,
          "tool": "pen",
          "opacity": 1.0,
          "smoothness": 1
        },
        {
          "points": [
            [
              370.20000000000005,
              141.60000000000002,
              1.0
            ],
            [
              371.0,
              155.2,
              1.0
            ],
            [
              379.0,
              203.20000000000005,
              1.0
            ],
            [
              380.6,
              249.60000000000002,
              1.0
            ],
            [
              382.20000000000005,
              280.0,
              1.0
            ],
            [
              382.20000000000005,
              294.4000000000001,
              1.0
            ],
            [
              381.40000000000003,
              311.20000000000005,
              1.0
            ],
            [
              380.6,
              328.0,
              1.0
            ],
            [
              378.20000000000005,
              344.0,
              1.0
            ],
            [
              375.8,
              354.40000000000003,
              1.0
            ],
            [
              374.20000000000005,
              368.0,
              1.0
            ],
            [
              371.0,
              373.6,
              1.0
            ],
            [
              367.8,
              378.40000000000003,
              1.0
            ],
            [
              366.20000000000005,
              381.6,
              1.0
            ],
            [
              364.6,
              384.8,
              1.0
            ],
            [
              363.0,
              387.20000000000005,
              1.0
            ],
            [
              361.4000000000001,
              389.6,
              1.0
            ],
            [
              361.4000000000001,
              390.40000000000003,
              1.0
            ],
            [
              359.8,
              391.20000000000005,
              1.0
            ],
            [
              359.0,
              392.0,
              1.0
            ],
            [
              359.0,
              392.8,
              1.0
            ],
            [
              358.20000000000005,
              392.8,
              1.0
            ],
            [
              357.4000000000001,
              392.8,
              1.0
            ],
            [
              356.6,
              392.8,
              1.0
            ],
            [
              355.0,
              391.20000000000005,
              1.0
            ],
            [
              354.20000000000005,
              388.0,
              1.0
            ],
            [
              354.20000000000005,
              382.40000000000003,
              1.0
            ],
            [
              353.4000000000001,
              371.20000000000005,
              1.0
            ],
            [
              352.6,
              360.8,
              1.0
            ],
            [
              352.6,
              351.20000000000005,
              1.0
            ],
            [
              352.6,
              344.8,
              1.0
            ],
            [
              352.6,
              339.20000000000005,
              1.0
            ],
            [
              353.4000000000001,
              336.8,
              1.0
            ],
            [
              356.6,
              334.40000000000003,
              1.0
            ],
            [
              359.0,
              332.8,
              1.0
            ],
            [
              366.20000000000005,
              330.40000000000003,
              1.0
            ],
            [
              378.20000000000005,
              328.8,
              1.0
            ],
            [
              392.6,
              328.0,
              1.0
            ],
            [
              404.6,
              328.0,
              1.0
            ],
            [
              428.6,
              328.0,
              1.0
            ],
            [
              448.6,
              328.8,
              1.0
            ],
            [
              466.20000000000005,
              329.6,
              1.0
            ],
            [
              476.6,
              329.6,
              1.0
            ],
            [
              488.6,
              329.6,
              1.0
            ],
            [
              499.0,
              329.6,
              1.0
            ],
            [
              504.6,
              329.6,
              1.0
            ],
            [
              508.6,
              329.6,
              1.0
            ],
            [
              511.80000000000007,
              329.6,
              1.0
            ],
            [
              515.0,
              328.8,
              1.0
            ],
            [
              517.4,
              328.0,
              1.0
            ],
            [
              518.2,
              328.0,
              1.0
            ],
            [
              519.8000000000001,
              328.0,
              1.0
            ],
            [
              522.2,
              326.40000000000003,
              1.0
            ],
            [
              523.0,
              325.6,
              1.0
            ],
            [
              523.8000000000001,
              324.0,
              1.0
            ],
            [
              526.2,
              322.40000000000003,
              1.0
            ],
            [
              528.6,
              320.0,
              1.0
            ],
            [
              530.2,
              318.40000000000003,
              1.0
            ],
            [
              531.0,
              316.8,
              1.0
            ],
            [
              531.8000000000001,
              314.40000000000003,
              1.0
            ],
            [
              534.2,
              312.8,
              1.0
            ],
            [
              534.2,
              310.40000000000003,
              1.0
            ],
            [
              535.8000000000001,
              310.40000000000003,
              1.0
            ],
            [
              535.8000000000001,
              309.6,
              1.0
            ],
            [
              536.6,
              308.8,
              1.0
            ]
          ],
          "color": "#0000ff",
          "width": 10.0,
          "tool": "pen",
          "opacity": 1.0,
          "smoothness": 1
        }
      ],
      "shapes": [],
      "images": [],
      "background_type": "dots",
      "background_color": "#1e1e1e"
    }
  ],
  "current_page": 0
}